pytme-0.3.3.data/scripts/estimate_memory_usage.py
pytme-0.3.3.data/scripts/estimate_ram_usage.py
pytme-0.3.3.data/scripts/match_template.py
pytme-0.3.3.data/scripts/postprocess.py
pytme-0.3.3.data/scripts/preprocess.py
pytme-0.3.3.data/scripts/preprocessor_gui.py
pytme-0.3.3.data/scripts/pytme_runner.py
pytme-0.3.3.dist-info/licenses/LICENSE
scripts/__init__.py
scripts/estimate_memory_usage.py
scripts/estimate_ram_usage.py
scripts/eval.py
scripts/extract_candidates.py
scripts/match_template.py
scripts/match_template_devel.py
scripts/match_template_filters.py
scripts/postprocess.py
scripts/preprocess.py
scripts/preprocessor_gui.py
scripts/pytme_runner.py
scripts/refine_matches.py
tests/__init__.py
tests/test_analyzer.py
tests/test_backends.py
tests/test_density.py
tests/test_extensions.py
tests/test_matching_cli.py
tests/test_matching_data.py
tests/test_matching_exhaustive.py
tests/test_matching_memory.py
tests/test_matching_optimization.py
tests/test_matching_utils.py
tests/test_orientations.py
tests/test_parser.py
tests/test_rotations.py
tests/test_structure.py
tests/data/.DS_Store
tests/data/README.md
tests/data/Blurring/.DS_Store
tests/data/Blurring/blob_width18.npy
tests/data/Blurring/edgegaussian_sigma3.npy
tests/data/Blurring/gaussian_sigma2.npy
tests/data/Blurring/hamming_width6.npy
tests/data/Blurring/kaiserb_width18.npy
tests/data/Blurring/localgaussian_sigma0510.npy
tests/data/Blurring/mean_size5.npy
tests/data/Blurring/ntree_sigma0510.npy
tests/data/Blurring/rank_rank3.npy
tests/data/Maps/.DS_Store
tests/data/Maps/emd_8621.mrc.gz
tests/data/Raw/.DS_Store
tests/data/Raw/em_map.map
tests/data/Structures/.DS_Store
tests/data/Structures/1pdj.cif
tests/data/Structures/1pdj.pdb
tests/data/Structures/5khe.cif
tests/data/Structures/5khe.ent
tests/data/Structures/5khe.pdb
tests/data/Structures/5uz4.cif
tests/preprocessing/__init__.py
tests/preprocessing/test_compose.py
tests/preprocessing/test_frequency_filters.py
tests/preprocessing/test_preprocessor.py
tests/preprocessing/test_utils.py
pytme-0.3.3.dist-info/METADATA
pytme-0.3.3.dist-info/WHEEL
pytme-0.3.3.dist-info/entry_points.txt
pytme-0.3.3.dist-info/top_level.txt
pytme-0.3.3.dist-info/RECORD
