Metadata-Version: 2.4
Name: pytme
Version: 0.3.3
Summary: Python Template Matching Engine
Author: Valentin Maurer
Author-email: Valentin Maurer <valentin.maurer@embl-hamburg.de>
License-Expression: GPL-2.0-only
Project-URL: Homepage, https://github.com/KosinskiLab/pyTME
Classifier: Programming Language :: Python :: 3
Classifier: Operating System :: OS Independent
Requires-Python: >=3.11
License-File: LICENSE
Requires-Dist: mrcfile>=1.4.3
Requires-Dist: numpy>=1.22.2
Requires-Dist: scipy>=1.9.1
Requires-Dist: pyfftw>=0.13.1
Requires-Dist: pytest>=6.2.5
Requires-Dist: PyYAML>=6.0
Requires-Dist: scikit-image>=0.19.0
Requires-Dist: scikit_learn>=1.2.1
Requires-Dist: pybind11
Requires-Dist: psutil
Requires-Dist: h5py
Requires-Dist: importlib_resources
Requires-Dist: joblib
Requires-Dist: pydantic
Provides-Extra: cupy
Requires-Dist: cupy-cuda12x>13.0.0; extra == "cupy"
Requires-Dist: voltools; extra == "cupy"
Provides-Extra: pytorch
Requires-Dist: torch; extra == "pytorch"
Requires-Dist: torchvision; extra == "pytorch"
Provides-Extra: jax
Requires-Dist: jax[cuda12]; extra == "jax"
Requires-Dist: jaxlib; extra == "jax"
Provides-Extra: jax-cpu
Requires-Dist: jax; extra == "jax-cpu"
Requires-Dist: jaxlib; extra == "jax-cpu"
Provides-Extra: mlx
Requires-Dist: mlx; extra == "mlx"
Dynamic: author
Dynamic: license-file
